phph/BlockUniformization.py
phph/LocalStateSpace.py
phph/Queue.py
phph/SubMatrices.py
phph/Uniformization.py
phph/__init__.py
phph/model.py
phph-0.1.dist-info/LICENSE
phph-0.1.dist-info/METADATA
phph-0.1.dist-info/WHEEL
phph-0.1.dist-info/top_level.txt
phph-0.1.dist-info/RECORD
