Metadata-Version: 2.1
Name: phph
Version: 0.1
Summary: A Python package for PH/PH/c queueing systems
Author-email: Anders Reenberg Andersen <andersra@live.dk>
Project-URL: Homepage, https://github.com/areenberg/phph
Project-URL: Issues, https://github.com/areenberg/phph/issues
Classifier: Development Status :: 3 - Alpha
Classifier: Programming Language :: Python :: 3
Classifier: License :: OSI Approved :: MIT License
Classifier: Operating System :: OS Independent
Requires-Python: >=3.10
License-File: LICENSE
Requires-Dist: numpy >=1.24.2
Requires-Dist: scipy >=1.10.1
